stark/__init__.py
stark/extract.py
stark/reduce.py
stark/version.py
stark/tests/__init__.py
stark_package-0.4.1.dist-info/LICENSE.rst
stark_package-0.4.1.dist-info/METADATA
stark_package-0.4.1.dist-info/WHEEL
stark_package-0.4.1.dist-info/top_level.txt
stark_package-0.4.1.dist-info/RECORD
