Metadata-Version: 2.1
Name: stark-package
Version: 0.4.1
Summary: Spectral exTraction And Reduction Kit
Home-page: https://github.com/Jayshil/stark
Author: Jayshil A. Patel, Alexis Brandeker, Gayathri Viswanath, Maria Cavallius, Markus Janson
Author-email: jayshil.patel@astro.su.se
License: Apache Software License 2.0
Requires-Python: >=3.7
License-File: licenses/LICENSE.rst
Requires-Dist: numpy
Requires-Dist: astropy
Requires-Dist: scipy
Requires-Dist: tqdm
Requires-Dist: scikit-image
Provides-Extra: all
Requires-Dist: numpy ; extra == 'all'
Requires-Dist: astropy ; extra == 'all'
Requires-Dist: scipy ; extra == 'all'
Requires-Dist: tqdm ; extra == 'all'
Requires-Dist: scikit-image ; extra == 'all'
Provides-Extra: docs
Requires-Dist: sphinx ; extra == 'docs'
Requires-Dist: sphinx-automodapi ; extra == 'docs'
Requires-Dist: sphinx-astropy ; extra == 'docs'
Requires-Dist: sphinx-rtd-theme ; extra == 'docs'
Provides-Extra: test
Requires-Dist: pytest ; extra == 'test'
Requires-Dist: pytest-doctestplus ; extra == 'test'
Requires-Dist: pytest-cov ; extra == 'test'
